{
  "date": "2026-04-13",
  "generated_at": "2026-04-13T18:46:01.117209",
  "filter_defaults": {
    "min_trading_value": 1000,
    "min_change_rate": -30.0,
    "max_change_rate": 30.0,
    "max_market_cap": 20000000
  },
  "total_filtered": 83,
  "stocks": [
    {
      "ticker": "005930",
      "name": "삼성전자",
      "market": "KOSPI",
      "close": 201000,
      "volume": 18853050,
      "trading_value": 37895.0,
      "market_cap": 11898472.0,
      "change_rate": -2.43,
      "one_month_return": 9.5,
      "two_month_return": 12.5,
      "three_month_return": 46.1
    },
    {
      "ticker": "000660",
      "name": "SK하이닉스",
      "market": "KOSPI",
      "close": 1040000,
      "volume": 2769188,
      "trading_value": 28800.0,
      "market_cap": 7412105.0,
      "change_rate": 1.27,
      "one_month_return": 14.3,
      "two_month_return": 17.1,
      "three_month_return": 40.9
    },
    {
      "ticker": "010170",
      "name": "대한광통신",
      "market": "KOSDAQ",
      "close": 19870,
      "volume": 57345309,
      "trading_value": 11395.0,
      "market_cap": 30895.0,
      "change_rate": 11.82,
      "one_month_return": 168.5,
      "two_month_return": 497.6,
      "three_month_return": 528.8
    },
    {
      "ticker": "122630",
      "name": "KODEX 레버리지",
      "market": "KOSPI",
      "close": 88845,
      "volume": 10736760,
      "trading_value": 9539.0,
      "market_cap": 58282.0,
      "change_rate": -1.99,
      "one_month_return": 11.4,
      "two_month_return": 4.8,
      "three_month_return": 47.7
    },
    {
      "ticker": "069500",
      "name": "KODEX 200",
      "market": "KOSPI",
      "close": 87880,
      "volume": 10570094,
      "trading_value": 9289.0,
      "market_cap": 202607.0,
      "change_rate": -0.87,
      "one_month_return": 7.8,
      "two_month_return": 7.2,
      "three_month_return": 28.4
    },
    {
      "ticker": "047040",
      "name": "대우건설",
      "market": "KOSPI",
      "close": 23750,
      "volume": 31437233,
      "trading_value": 7466.0,
      "market_cap": 97591.0,
      "change_rate": -2.26,
      "one_month_return": 92.8,
      "two_month_return": 208.4,
      "three_month_return": 525.0
    },
    {
      "ticker": "252670",
      "name": "KODEX 200선물인버스2X",
      "market": "KOSPI",
      "close": 224,
      "volume": 2782204089,
      "trading_value": 6232.0,
      "market_cap": 11769.0,
      "change_rate": 2.28,
      "one_month_return": -21.1,
      "two_month_return": -30.0,
      "three_month_return": -53.7
    },
    {
      "ticker": "008350",
      "name": "남선알미늄",
      "market": "KOSPI",
      "close": 2865,
      "volume": 196784066,
      "trading_value": 5638.0,
      "market_cap": 3698.0,
      "change_rate": 29.93,
      "one_month_return": 90.2,
      "two_month_return": 123.7,
      "three_month_return": 137.6
    },
    {
      "ticker": "490470",
      "name": "세미파이브",
      "market": "KOSDAQ",
      "close": 36500,
      "volume": 14490373,
      "trading_value": 5289.0,
      "market_cap": 12358.0,
      "change_rate": 16.61,
      "one_month_return": 43.1,
      "two_month_return": 33.2,
      "three_month_return": 42.6
    },
    {
      "ticker": "010120",
      "name": "LS ELECTRIC",
      "market": "KOSPI",
      "close": 179200,
      "volume": 2572650,
      "trading_value": 4610.0,
      "market_cap": 268800.0,
      "change_rate": 13.71,
      "one_month_return": -76.0,
      "two_month_return": -73.3,
      "three_month_return": -63.9
    },
    {
      "ticker": "459580",
      "name": "KODEX CD금리액티브(합성)",
      "market": "KOSPI",
      "close": 1074445,
      "volume": 408260,
      "trading_value": 4387.0,
      "market_cap": 81216.0,
      "change_rate": 0.01,
      "one_month_return": 0.0,
      "two_month_return": -0.0,
      "three_month_return": -0.0
    },
    {
      "ticker": "379800",
      "name": "KODEX 미국S&P500",
      "market": "KOSPI",
      "close": 22905,
      "volume": 17644166,
      "trading_value": 4041.0,
      "market_cap": 81966.0,
      "change_rate": -0.17,
      "one_month_return": 1.2,
      "two_month_return": 0.8,
      "three_month_return": -2.1
    },
    {
      "ticker": "050890",
      "name": "쏠리드",
      "market": "KOSDAQ",
      "close": 17350,
      "volume": 22972656,
      "trading_value": 3986.0,
      "market_cap": 10541.0,
      "change_rate": 1.58,
      "one_month_return": 36.1,
      "two_month_return": 87.2,
      "three_month_return": 138.0
    },
    {
      "ticker": "360750",
      "name": "TIGER 미국S&P500",
      "market": "KOSPI",
      "close": 25065,
      "volume": 15827467,
      "trading_value": 3967.0,
      "market_cap": 155403.0,
      "change_rate": -0.16,
      "one_month_return": 1.2,
      "two_month_return": 0.7,
      "three_month_return": -1.8
    },
    {
      "ticker": "079550",
      "name": "LIG넥스원",
      "market": "KOSPI",
      "close": 939000,
      "volume": 379317,
      "trading_value": 3562.0,
      "market_cap": 206580.0,
      "change_rate": 1.95,
      "one_month_return": 29.9,
      "two_month_return": 106.1,
      "three_month_return": 64.7
    },
    {
      "ticker": "046970",
      "name": "우리로",
      "market": "KOSDAQ",
      "close": 9990,
      "volume": 34203750,
      "trading_value": 3417.0,
      "market_cap": 4378.0,
      "change_rate": 29.91,
      "one_month_return": 548.3,
      "two_month_return": 590.4,
      "three_month_return": 637.8
    },
    {
      "ticker": "114800",
      "name": "KODEX 인버스",
      "market": "KOSPI",
      "close": 1545,
      "volume": 200335170,
      "trading_value": 3095.0,
      "market_cap": 9378.0,
      "change_rate": 0.98,
      "one_month_return": -9.7,
      "two_month_return": -13.1,
      "three_month_return": -28.5
    },
    {
      "ticker": "005380",
      "name": "현대차",
      "market": "KOSPI",
      "close": 478500,
      "volume": 636025,
      "trading_value": 3043.0,
      "market_cap": 979766.0,
      "change_rate": -2.25,
      "one_month_return": -7.4,
      "two_month_return": -5.4,
      "three_month_return": 17.9
    },
    {
      "ticker": "025860",
      "name": "남해화학",
      "market": "KOSPI",
      "close": 9390,
      "volume": 31935662,
      "trading_value": 2999.0,
      "market_cap": 4665.0,
      "change_rate": 18.26,
      "one_month_return": 4.9,
      "two_month_return": 27.6,
      "three_month_return": 42.1
    },
    {
      "ticker": "009150",
      "name": "삼성전기",
      "market": "KOSPI",
      "close": 568000,
      "volume": 515832,
      "trading_value": 2930.0,
      "market_cap": 424260.0,
      "change_rate": 0.53,
      "one_month_return": 41.8,
      "two_month_return": 77.8,
      "three_month_return": 96.5
    },
    {
      "ticker": "396500",
      "name": "TIGER 반도체TOP10",
      "market": "KOSPI",
      "close": 33750,
      "volume": 8582470,
      "trading_value": 2897.0,
      "market_cap": 92053.0,
      "change_rate": -0.87,
      "one_month_return": 4.3,
      "two_month_return": 14.6,
      "three_month_return": 45.4
    },
    {
      "ticker": "011930",
      "name": "신성이엔지",
      "market": "KOSPI",
      "close": 3925,
      "volume": 73379555,
      "trading_value": 2880.0,
      "market_cap": 8080.0,
      "change_rate": 3.7,
      "one_month_return": 65.6,
      "two_month_return": 59.9,
      "three_month_return": 148.9
    },
    {
      "ticker": "379810",
      "name": "KODEX 미국나스닥100",
      "market": "KOSPI",
      "close": 24675,
      "volume": 11635233,
      "trading_value": 2871.0,
      "market_cap": 61934.0,
      "change_rate": -0.02,
      "one_month_return": 1.4,
      "two_month_return": 2.3,
      "three_month_return": -2.3
    },
    {
      "ticker": "005880",
      "name": "대한해운",
      "market": "KOSPI",
      "close": 2860,
      "volume": 98757265,
      "trading_value": 2824.0,
      "market_cap": 9231.0,
      "change_rate": -7.44,
      "one_month_return": 30.0,
      "two_month_return": 29.4,
      "three_month_return": 59.3
    },
    {
      "ticker": "018470",
      "name": "조일알미늄",
      "market": "KOSPI",
      "close": 1917,
      "volume": 145657570,
      "trading_value": 2792.0,
      "market_cap": 2428.0,
      "change_rate": 26.62,
      "one_month_return": 51.7,
      "two_month_return": 50.9,
      "three_month_return": 49.5
    },
    {
      "ticker": "005935",
      "name": "삼성전자우",
      "market": "KOSPI",
      "close": 138500,
      "volume": 1986208,
      "trading_value": 2751.0,
      "market_cap": 1130125.0,
      "change_rate": -1.35,
      "one_month_return": 3.4,
      "two_month_return": 13.4,
      "three_month_return": 34.2
    },
    {
      "ticker": "012450",
      "name": "한화에어로스페이스",
      "market": "KOSPI",
      "close": 1530000,
      "volume": 165048,
      "trading_value": 2525.0,
      "market_cap": 788920.0,
      "change_rate": 1.53,
      "one_month_return": 2.8,
      "two_month_return": 35.3,
      "three_month_return": 19.3
    },
    {
      "ticker": "229200",
      "name": "KODEX 코스닥150",
      "market": "KOSPI",
      "close": 18540,
      "volume": 13614001,
      "trading_value": 2524.0,
      "market_cap": 66067.0,
      "change_rate": -0.19,
      "one_month_return": -7.0,
      "two_month_return": -4.2,
      "three_month_return": 16.8
    },
    {
      "ticker": "010820",
      "name": "퍼스텍",
      "market": "KOSPI",
      "close": 12000,
      "volume": 20925562,
      "trading_value": 2511.0,
      "market_cap": 5853.0,
      "change_rate": 5.36,
      "one_month_return": 64.2,
      "two_month_return": 140.2,
      "three_month_return": 203.4
    },
    {
      "ticker": "233740",
      "name": "KODEX 코스닥150레버리지",
      "market": "KOSPI",
      "close": 14505,
      "volume": 17167008,
      "trading_value": 2490.0,
      "market_cap": 40599.0,
      "change_rate": -0.14,
      "one_month_return": -15.4,
      "two_month_return": -16.7,
      "three_month_return": 20.5
    },
    {
      "ticker": "091160",
      "name": "KODEX 반도체",
      "market": "KOSPI",
      "close": 103055,
      "volume": 2396923,
      "trading_value": 2470.0,
      "market_cap": 42304.0,
      "change_rate": 0.05,
      "one_month_return": 6.3,
      "two_month_return": 15.3,
      "three_month_return": 48.5
    },
    {
      "ticker": "402340",
      "name": "SK스퀘어",
      "market": "KOSPI",
      "close": 580000,
      "volume": 404119,
      "trading_value": 2344.0,
      "market_cap": 766105.0,
      "change_rate": 2.11,
      "one_month_return": 8.6,
      "two_month_return": 1.8,
      "three_month_return": 36.0
    },
    {
      "ticker": "006400",
      "name": "삼성SDI",
      "market": "KOSPI",
      "close": 477500,
      "volume": 482539,
      "trading_value": 2304.0,
      "market_cap": 384796.0,
      "change_rate": -0.73,
      "one_month_return": 23.1,
      "two_month_return": 23.9,
      "three_month_return": 59.2
    },
    {
      "ticker": "102110",
      "name": "TIGER 200",
      "market": "KOSPI",
      "close": 87820,
      "volume": 2587339,
      "trading_value": 2272.0,
      "market_cap": 77545.0,
      "change_rate": -1.0,
      "one_month_return": 7.6,
      "two_month_return": 7.2,
      "three_month_return": 28.2
    },
    {
      "ticker": "487240",
      "name": "KODEX AI전력핵심설비",
      "market": "KOSPI",
      "close": 35335,
      "volume": 6366532,
      "trading_value": 2250.0,
      "market_cap": 21943.0,
      "change_rate": 4.11,
      "one_month_return": 12.8,
      "two_month_return": 17.4,
      "three_month_return": 39.3
    },
    {
      "ticker": "494310",
      "name": "KODEX 반도체레버리지",
      "market": "KOSPI",
      "close": 69700,
      "volume": 3202298,
      "trading_value": 2232.0,
      "market_cap": 13487.0,
      "change_rate": -0.54,
      "one_month_return": 7.2,
      "two_month_return": 19.2,
      "three_month_return": 86.0
    },
    {
      "ticker": "115440",
      "name": "우리넷",
      "market": "KOSDAQ",
      "close": 16900,
      "volume": 12898005,
      "trading_value": 2180.0,
      "market_cap": 1824.0,
      "change_rate": 30.0,
      "one_month_return": 123.0,
      "two_month_return": 137.7,
      "three_month_return": 122.4
    },
    {
      "ticker": "062040",
      "name": "산일전기",
      "market": "KOSPI",
      "close": 172900,
      "volume": 1250177,
      "trading_value": 2162.0,
      "market_cap": 52935.0,
      "change_rate": 12.64,
      "one_month_return": 23.0,
      "two_month_return": 13.3,
      "three_month_return": 23.5
    },
    {
      "ticker": "032820",
      "name": "우리기술",
      "market": "KOSDAQ",
      "close": 21100,
      "volume": 9930149,
      "trading_value": 2095.0,
      "market_cap": 36101.0,
      "change_rate": 0.48,
      "one_month_return": -13.7,
      "two_month_return": 54.9,
      "three_month_return": 425.5
    },
    {
      "ticker": "100790",
      "name": "미래에셋벤처투자",
      "market": "KOSDAQ",
      "close": 29950,
      "volume": 6528126,
      "trading_value": 1955.0,
      "market_cap": 15911.0,
      "change_rate": 7.16,
      "one_month_return": 36.1,
      "two_month_return": 33.7,
      "three_month_return": 128.6
    },
    {
      "ticker": "000250",
      "name": "삼천당제약",
      "market": "KOSDAQ",
      "close": 526000,
      "volume": 371231,
      "trading_value": 1953.0,
      "market_cap": 123386.0,
      "change_rate": 4.16,
      "one_month_return": -31.9,
      "two_month_return": 1.0,
      "three_month_return": 95.2
    },
    {
      "ticker": "498400",
      "name": "KODEX 200타겟위클리커버드콜",
      "market": "KOSPI",
      "close": 18335,
      "volume": 10210322,
      "trading_value": 1872.0,
      "market_cap": 41254.0,
      "change_rate": -0.52,
      "one_month_return": 7.7,
      "two_month_return": 5.7,
      "three_month_return": 20.8
    },
    {
      "ticker": "034020",
      "name": "두산에너빌리티",
      "market": "KOSPI",
      "close": 99300,
      "volume": 1746075,
      "trading_value": 1734.0,
      "market_cap": 636077.0,
      "change_rate": -0.9,
      "one_month_return": -6.8,
      "two_month_return": 4.0,
      "three_month_return": 14.1
    },
    {
      "ticker": "298040",
      "name": "효성중공업",
      "market": "KOSPI",
      "close": 3058000,
      "volume": 56040,
      "trading_value": 1714.0,
      "market_cap": 285145.0,
      "change_rate": 4.01,
      "one_month_return": 17.9,
      "two_month_return": 27.2,
      "three_month_return": 50.5
    },
    {
      "ticker": "403870",
      "name": "HPSP",
      "market": "KOSDAQ",
      "close": 41400,
      "volume": 4139134,
      "trading_value": 1714.0,
      "market_cap": 34072.0,
      "change_rate": -9.11,
      "one_month_return": -2.9,
      "two_month_return": -2.6,
      "three_month_return": 23.8
    },
    {
      "ticker": "488080",
      "name": "TIGER 반도체TOP10레버리지",
      "market": "KOSPI",
      "close": 42680,
      "volume": 3734046,
      "trading_value": 1594.0,
      "market_cap": 14789.0,
      "change_rate": -1.43,
      "one_month_return": 4.8,
      "two_month_return": 18.6,
      "three_month_return": 83.5
    },
    {
      "ticker": "088800",
      "name": "에이스테크",
      "market": "KOSDAQ",
      "close": 6720,
      "volume": 23680133,
      "trading_value": 1591.0,
      "market_cap": 5074.0,
      "change_rate": 20.21,
      "one_month_return": 86.7,
      "two_month_return": 132.9,
      "three_month_return": 130.9
    },
    {
      "ticker": "000720",
      "name": "현대건설",
      "market": "KOSPI",
      "close": 176000,
      "volume": 887344,
      "trading_value": 1562.0,
      "market_cap": 195986.0,
      "change_rate": -1.95,
      "one_month_return": 7.1,
      "two_month_return": 52.5,
      "three_month_return": 91.3
    },
    {
      "ticker": "028050",
      "name": "삼성E&A",
      "market": "KOSPI",
      "close": 49550,
      "volume": 3119606,
      "trading_value": 1546.0,
      "market_cap": 97118.0,
      "change_rate": -3.22,
      "one_month_return": 51.1,
      "two_month_return": 46.6,
      "three_month_return": 94.3
    },
    {
      "ticker": "095340",
      "name": "ISC",
      "market": "KOSDAQ",
      "close": 216500,
      "volume": 682724,
      "trading_value": 1478.0,
      "market_cap": 45892.0,
      "change_rate": -15.92,
      "one_month_return": 16.8,
      "two_month_return": 23.3,
      "three_month_return": 98.8
    },
    {
      "ticker": "215790",
      "name": "이노인스트루먼트",
      "market": "KOSDAQ",
      "close": 3340,
      "volume": 43437789,
      "trading_value": 1451.0,
      "market_cap": 1345.0,
      "change_rate": 14.19,
      "one_month_return": 772.1,
      "two_month_return": 558.8,
      "three_month_return": 441.3
    },
    {
      "ticker": "100590",
      "name": "머큐리",
      "market": "KOSDAQ",
      "close": 11320,
      "volume": 12749009,
      "trading_value": 1443.0,
      "market_cap": 1792.0,
      "change_rate": 21.85,
      "one_month_return": 118.5,
      "two_month_return": 214.4,
      "three_month_return": 256.0
    },
    {
      "ticker": "000270",
      "name": "기아",
      "market": "KOSPI",
      "close": 147400,
      "volume": 976438,
      "trading_value": 1439.0,
      "market_cap": 575469.0,
      "change_rate": -1.07,
      "one_month_return": -10.3,
      "two_month_return": -11.4,
      "three_month_return": 8.4
    },
    {
      "ticker": "272210",
      "name": "한화시스템",
      "market": "KOSPI",
      "close": 131900,
      "volume": 1072186,
      "trading_value": 1414.0,
      "market_cap": 249185.0,
      "change_rate": -1.05,
      "one_month_return": -8.7,
      "two_month_return": 24.7,
      "three_month_return": 48.7
    },
    {
      "ticker": "043260",
      "name": "성호전자",
      "market": "KOSDAQ",
      "close": 48000,
      "volume": 2860075,
      "trading_value": 1373.0,
      "market_cap": 34043.0,
      "change_rate": 7.99,
      "one_month_return": -4.8,
      "two_month_return": 109.6,
      "three_month_return": 251.4
    },
    {
      "ticker": "105560",
      "name": "KB금융",
      "market": "KOSPI",
      "close": 156600,
      "volume": 861811,
      "trading_value": 1350.0,
      "market_cap": 583884.0,
      "change_rate": -1.07,
      "one_month_return": 5.2,
      "two_month_return": -7.1,
      "three_month_return": 21.9
    },
    {
      "ticker": "066970",
      "name": "엘앤에프",
      "market": "KOSPI",
      "close": 181700,
      "volume": 737997,
      "trading_value": 1341.0,
      "market_cap": 73271.0,
      "change_rate": -2.73,
      "one_month_return": 70.1,
      "two_month_return": 53.1,
      "three_month_return": 54.9
    },
    {
      "ticker": "001440",
      "name": "대한전선",
      "market": "KOSPI",
      "close": 32000,
      "volume": 4091168,
      "trading_value": 1309.0,
      "market_cap": 59663.0,
      "change_rate": 0.95,
      "one_month_return": 6.8,
      "two_month_return": 0.5,
      "three_month_return": 20.8
    },
    {
      "ticker": "001780",
      "name": "알루코",
      "market": "KOSPI",
      "close": 2885,
      "volume": 45224521,
      "trading_value": 1305.0,
      "market_cap": 2794.0,
      "change_rate": 11.39,
      "one_month_return": 34.8,
      "two_month_return": 24.6,
      "three_month_return": 35.1
    },
    {
      "ticker": "375500",
      "name": "DL이앤씨",
      "market": "KOSPI",
      "close": 94500,
      "volume": 1299403,
      "trading_value": 1228.0,
      "market_cap": 36565.0,
      "change_rate": 0.0,
      "one_month_return": 92.7,
      "two_month_return": 89.8,
      "three_month_return": 126.1
    },
    {
      "ticker": "178320",
      "name": "서진시스템",
      "market": "KOSDAQ",
      "close": 47700,
      "volume": 2483342,
      "trading_value": 1185.0,
      "market_cap": 28258.0,
      "change_rate": 5.41,
      "one_month_return": 3.9,
      "two_month_return": 29.4,
      "three_month_return": 79.7
    },
    {
      "ticker": "086520",
      "name": "에코프로",
      "market": "KOSDAQ",
      "close": 143700,
      "volume": 822112,
      "trading_value": 1181.0,
      "market_cap": 195110.0,
      "change_rate": -1.84,
      "one_month_return": -4.5,
      "two_month_return": -7.6,
      "three_month_return": 47.7
    },
    {
      "ticker": "017670",
      "name": "SK텔레콤",
      "market": "KOSPI",
      "close": 92500,
      "volume": 1269068,
      "trading_value": 1174.0,
      "market_cap": 198681.0,
      "change_rate": -0.54,
      "one_month_return": 23.3,
      "two_month_return": 18.6,
      "three_month_return": 70.3
    },
    {
      "ticker": "133690",
      "name": "TIGER 미국나스닥100",
      "market": "KOSPI",
      "close": 164680,
      "volume": 706586,
      "trading_value": 1164.0,
      "market_cap": 83180.0,
      "change_rate": -0.04,
      "one_month_return": 1.4,
      "two_month_return": 2.2,
      "three_month_return": -2.2
    },
    {
      "ticker": "0177N0",
      "name": "KODEX 삼성전자SK하이닉스채권혼합50",
      "market": "KOSPI",
      "close": 11185,
      "volume": 10392672,
      "trading_value": 1162.0,
      "market_cap": 3356.0,
      "change_rate": -0.4,
      "one_month_return": null,
      "two_month_return": null,
      "three_month_return": null
    },
    {
      "ticker": "064350",
      "name": "현대로템",
      "market": "KOSPI",
      "close": 207000,
      "volume": 554242,
      "trading_value": 1147.0,
      "market_cap": 225925.0,
      "change_rate": -1.43,
      "one_month_return": 4.3,
      "two_month_return": 0.5,
      "three_month_return": -10.8
    },
    {
      "ticker": "028260",
      "name": "삼성물산",
      "market": "KOSPI",
      "close": 289500,
      "volume": 395949,
      "trading_value": 1146.0,
      "market_cap": 469479.0,
      "change_rate": -4.3,
      "one_month_return": 3.2,
      "two_month_return": -13.3,
      "three_month_return": 5.9
    },
    {
      "ticker": "278470",
      "name": "에이피알",
      "market": "KOSPI",
      "close": 399500,
      "volume": 286905,
      "trading_value": 1146.0,
      "market_cap": 149565.0,
      "change_rate": 1.65,
      "one_month_return": 16.6,
      "two_month_return": 41.7,
      "three_month_return": 78.7
    },
    {
      "ticker": "267260",
      "name": "HD현대일렉트릭",
      "market": "KOSPI",
      "close": 1007000,
      "volume": 112646,
      "trading_value": 1134.0,
      "market_cap": 362995.0,
      "change_rate": 0.8,
      "one_month_return": 8.4,
      "two_month_return": 4.2,
      "three_month_return": 13.7
    },
    {
      "ticker": "005290",
      "name": "동진쎄미켐",
      "market": "KOSDAQ",
      "close": 52200,
      "volume": 2168331,
      "trading_value": 1132.0,
      "market_cap": 26838.0,
      "change_rate": 5.45,
      "one_month_return": 4.2,
      "two_month_return": -0.9,
      "three_month_return": 30.8
    },
    {
      "ticker": "007660",
      "name": "이수페타시스",
      "market": "KOSPI",
      "close": 119700,
      "volume": 943329,
      "trading_value": 1129.0,
      "market_cap": 87871.0,
      "change_rate": 4.18,
      "one_month_return": 11.8,
      "two_month_return": 10.6,
      "three_month_return": 2.9
    },
    {
      "ticker": "148020",
      "name": "RISE 200",
      "market": "KOSPI",
      "close": 88655,
      "volume": 1249838,
      "trading_value": 1108.0,
      "market_cap": 34176.0,
      "change_rate": -0.94,
      "one_month_return": 7.6,
      "two_month_return": 7.3,
      "three_month_return": 28.3
    },
    {
      "ticker": "329180",
      "name": "HD현대중공업",
      "market": "KOSPI",
      "close": 463000,
      "volume": 238785,
      "trading_value": 1106.0,
      "market_cap": 485970.0,
      "change_rate": -2.53,
      "one_month_return": -22.3,
      "two_month_return": -14.1,
      "three_month_return": -28.2
    },
    {
      "ticker": "003280",
      "name": "흥아해운",
      "market": "KOSPI",
      "close": 3430,
      "volume": 31962468,
      "trading_value": 1096.0,
      "market_cap": 8247.0,
      "change_rate": 4.41,
      "one_month_return": 46.9,
      "two_month_return": 97.2,
      "three_month_return": 106.9
    },
    {
      "ticker": "042700",
      "name": "한미반도체",
      "market": "KOSPI",
      "close": 276500,
      "volume": 387276,
      "trading_value": 1071.0,
      "market_cap": 263538.0,
      "change_rate": -3.32,
      "one_month_return": -9.5,
      "two_month_return": 32.0,
      "three_month_return": 59.6
    },
    {
      "ticker": "006360",
      "name": "GS건설",
      "market": "KOSPI",
      "close": 36300,
      "volume": 2880124,
      "trading_value": 1045.0,
      "market_cap": 31066.0,
      "change_rate": -3.59,
      "one_month_return": 57.8,
      "two_month_return": 67.3,
      "three_month_return": 94.0
    },
    {
      "ticker": "462330",
      "name": "KODEX 2차전지산업레버리지",
      "market": "KOSPI",
      "close": 1839,
      "volume": 55723933,
      "trading_value": 1025.0,
      "market_cap": 8242.0,
      "change_rate": -4.22,
      "one_month_return": 17.0,
      "two_month_return": -6.6,
      "three_month_return": 22.8
    },
    {
      "ticker": "035420",
      "name": "NAVER",
      "market": "KOSPI",
      "close": 199000,
      "volume": 514728,
      "trading_value": 1024.0,
      "market_cap": 312137.0,
      "change_rate": -1.49,
      "one_month_return": -10.8,
      "two_month_return": -22.1,
      "three_month_return": -24.8
    },
    {
      "ticker": "005490",
      "name": "POSCO홀딩스",
      "market": "KOSPI",
      "close": 360000,
      "volume": 284457,
      "trading_value": 1024.0,
      "market_cap": 285269.0,
      "change_rate": -2.44,
      "one_month_return": 6.8,
      "two_month_return": -6.0,
      "three_month_return": 2.1
    },
    {
      "ticker": "006800",
      "name": "미래에셋증권",
      "market": "KOSPI",
      "close": 65300,
      "volume": 1563776,
      "trading_value": 1021.0,
      "market_cap": 362622.0,
      "change_rate": -1.8,
      "one_month_return": -6.0,
      "two_month_return": 22.3,
      "three_month_return": 129.5
    },
    {
      "ticker": "322000",
      "name": "HD현대에너지솔루션",
      "market": "KOSPI",
      "close": 160900,
      "volume": 631775,
      "trading_value": 1017.0,
      "market_cap": 18021.0,
      "change_rate": -4.45,
      "one_month_return": 31.8,
      "two_month_return": 85.2,
      "three_month_return": 177.4
    },
    {
      "ticker": "0117V0",
      "name": "TIGER 코리아AI전력기기TOP3플러스",
      "market": "KOSPI",
      "close": 19020,
      "volume": 5335026,
      "trading_value": 1015.0,
      "market_cap": 6952.0,
      "change_rate": 3.91,
      "one_month_return": 13.0,
      "two_month_return": 18.5,
      "three_month_return": 41.0
    },
    {
      "ticker": "217590",
      "name": "티엠씨",
      "market": "KOSPI",
      "close": 31450,
      "volume": 3190001,
      "trading_value": 1003.0,
      "market_cap": 7578.0,
      "change_rate": 29.96,
      "one_month_return": 104.1,
      "two_month_return": 114.1,
      "three_month_return": 133.8
    }
  ],
  "highlights": [
    "🚀 상한가: 남선알미늄(+29.93%)",
    "🚀 상한가: 우리로(+29.91%)",
    "🚀 상한가: 우리넷(+30.0%)",
    "🚀 상한가: 티엠씨(+29.96%)",
    "💰 거래대금 TOP3: 삼성전자(37895억), SK하이닉스(28800억), 대한광통신(11395억)",
    "🔥 급등(+15%↑) 9개 — 과열 주의",
    "⚠️ 단기 급등 지속 (추격 주의): 대한광통신 (3M +528.8%, 오늘 +11.82%), 남선알미늄 (3M +137.6%, 오늘 +29.93%), 우리로 (3M +637.8%, 오늘 +29.91%), 우리넷 (3M +122.4%, 오늘 +30.0%), 에이스테크 (3M +130.9%, 오늘 +20.21%), 이노인스트루먼트 (3M +441.3%, 오늘 +14.19%), 머큐리 (3M +256.0%, 오늘 +21.85%), 티엠씨 (3M +133.8%, 오늘 +29.96%)"
  ],
  "all_stocks_summary": {
    "kospi_count": 66,
    "kosdaq_count": 17,
    "total_kospi": 2431,
    "total_kosdaq": 1823,
    "total": 4254
  }
}